fakepy_mcp.py
fake_py_mcp-0.2.4.dist-info/licenses/LICENSE
fake_py_mcp-0.2.4.dist-info/METADATA
fake_py_mcp-0.2.4.dist-info/WHEEL
fake_py_mcp-0.2.4.dist-info/entry_points.txt
fake_py_mcp-0.2.4.dist-info/top_level.txt
fake_py_mcp-0.2.4.dist-info/RECORD
