Metadata-Version: 2.4
Name: fake-py-mcp
Version: 0.2.4
Summary: MCP server for fake.py.
Author-email: Artur Barseghyan <artur.barseghyan@gmail.com>
Maintainer-email: Artur Barseghyan <artur.barseghyan@gmail.com>
License-Expression: MIT
Project-URL: Homepage, https://github.com/barseghyanartur/fake-py-mcp/
Project-URL: Issues, https://github.com/barseghyanartur/fake-py-mcp/issues
Project-URL: Documentation, https://fake-py-mcp.readthedocs.io/
Project-URL: Repository, https://github.com/barseghyanartur/fake-py-mcp/
Project-URL: Changelog, https://fake-py-mcp.readthedocs.io/en/latest/changelog.html
Keywords: fake data,test data
Classifier: Development Status :: 4 - Beta
Classifier: Intended Audience :: Developers
Classifier: Operating System :: OS Independent
Classifier: Programming Language :: Python :: 3
Classifier: Programming Language :: Python :: 3.10
Classifier: Programming Language :: Python :: 3.11
Classifier: Programming Language :: Python :: 3.12
Classifier: Programming Language :: Python :: 3.13
Classifier: Programming Language :: Python
Classifier: Topic :: Software Development :: Testing
Classifier: Topic :: Software Development
License-File: LICENSE
Requires-Dist: fake.py
Requires-Dist: fastmcp
Provides-Extra: all
Requires-Dist: fake-py-mcp[dev,docs,test]; extra == "all"
Provides-Extra: dev
Requires-Dist: build; extra == "dev"
Requires-Dist: detect-secrets; extra == "dev"
Requires-Dist: doc8; extra == "dev"
Requires-Dist: ipython; extra == "dev"
Requires-Dist: mypy; extra == "dev"
Requires-Dist: pkginfo; extra == "dev"
Requires-Dist: pydoclint; extra == "dev"
Requires-Dist: ruff; extra == "dev"
Requires-Dist: twine; extra == "dev"
Requires-Dist: uv; extra == "dev"
Requires-Dist: wheel; extra == "dev"
Provides-Extra: test
Requires-Dist: pytest; extra == "test"
Requires-Dist: pytest-cov; extra == "test"
Requires-Dist: pytest-codeblock; extra == "test"
Requires-Dist: pytest-asyncio; extra == "test"
Requires-Dist: inline-snapshot; extra == "test"
Provides-Extra: docs
Requires-Dist: sphinx<6.0; extra == "docs"
Requires-Dist: sphinx-autobuild; extra == "docs"
Requires-Dist: sphinx-rtd-theme>=1.3.0; extra == "docs"
Requires-Dist: sphinx-no-pragma; extra == "docs"
Requires-Dist: PyYAML; extra == "docs"
Dynamic: license-file
